mac_mathpix_ocr/__init__.py
mac_mathpix_ocr/__main__.py
mac_mathpix_ocr/mac_mathpix_ocr.py
mac_mathpix_ocr/logx/__init__.py
mac_mathpix_ocr/logx/colored_handler.py
mac_mathpix_ocr/logx/logging.yaml
mac_mathpix_ocr/logx/setup_logging.py
mac_mathpix_ocr-0.0.1.dist-info/METADATA
mac_mathpix_ocr-0.0.1.dist-info/WHEEL
mac_mathpix_ocr-0.0.1.dist-info/entry_points.txt
mac_mathpix_ocr-0.0.1.dist-info/top_level.txt
mac_mathpix_ocr-0.0.1.dist-info/RECORD
